CONTRIBUTING.rst
HISTORY.rst
LICENSE
MANIFEST.in
README.rst
setup.cfg
setup.py
pyclashsub/__init__.py
pyclashsub/__main__.py
pyclashsub/pyclashsub.py
pyclashsub.egg-info/PKG-INFO
pyclashsub.egg-info/SOURCES.txt
pyclashsub.egg-info/dependency_links.txt
pyclashsub.egg-info/entry_points.txt
pyclashsub.egg-info/not-zip-safe
pyclashsub.egg-info/requires.txt
pyclashsub.egg-info/top_level.txt
tests/__init__.py
tests/test_pyclashsub.py