Metadata-Version: 2.1
Name: pyclashsub
Version: 0.2.1
Summary: A python clash subscriber script
Home-page: https://github.com/sorn/pyclashsub
Author: Hong-She Liang
Author-email: sorn@taorules.com
License: Apache Software License
Keywords: pyclashsub
Platform: UNKNOWN
Classifier: Development Status :: 2 - Pre-Alpha
Classifier: Intended Audience :: Developers
Classifier: License :: OSI Approved :: Apache Software License
Classifier: Programming Language :: Python :: 3
Classifier: Programming Language :: Python :: 3.5
Classifier: Programming Language :: Python :: 3.6
Classifier: Programming Language :: Python :: 3.7
License-File: LICENSE
